gavl/__init__.py
gavl/cli.py
gavl/constants.py
gavl/engine.py
gavl/nodes.py
gavl/parser/__init__.py
gavl/parser/nodes.py
gavl/parser/parser.py
gavl/parser/visitors.py
gavl/parser/tests/__init__.py
gavl/parser/tests/test_apply.py
gavl/parser/tests/test_filter.py
gavl/parser/tests/test_simple.py
gavl/relalg/__init__.py
gavl/relalg/nodes.py
gavl-0.1.7.dist-info/DESCRIPTION.rst
gavl-0.1.7.dist-info/METADATA
gavl-0.1.7.dist-info/RECORD
gavl-0.1.7.dist-info/WHEEL
gavl-0.1.7.dist-info/entry_points.txt
gavl-0.1.7.dist-info/metadata.json
gavl-0.1.7.dist-info/top_level.txt
