Metadata-Version: 2.0
Name: gavl
Version: 0.1.7
Summary: Data definition language and aggregation layer
Home-page: UNKNOWN
Author: UNKNOWN
Author-email: UNKNOWN
License: Apache-2.0
Platform: UNKNOWN
Classifier: License :: OSI Approved :: Apache Software License
Requires-Dist: click
Requires-Dist: pandas
Requires-Dist: pyparsing
Requires-Dist: sqlalchemy
